teaspoons_client/__init__.py
teaspoons_client/api_client.py
teaspoons_client/api_response.py
teaspoons_client/configuration.py
teaspoons_client/exceptions.py
teaspoons_client/py.typed
teaspoons_client/rest.py
teaspoons_client/api/__init__.py
teaspoons_client/api/admin_api.py
teaspoons_client/api/jobs_api.py
teaspoons_client/api/pipeline_runs_api.py
teaspoons_client/api/pipelines_api.py
teaspoons_client/api/public_api.py
teaspoons_client/models/__init__.py
teaspoons_client/models/admin_pipeline.py
teaspoons_client/models/async_pipeline_run_response.py
teaspoons_client/models/error_report.py
teaspoons_client/models/get_jobs_response.py
teaspoons_client/models/get_pipeline_runs_response.py
teaspoons_client/models/get_pipelines_result.py
teaspoons_client/models/job_control.py
teaspoons_client/models/job_report.py
teaspoons_client/models/job_result.py
teaspoons_client/models/pipeline.py
teaspoons_client/models/pipeline_run.py
teaspoons_client/models/pipeline_run_report.py
teaspoons_client/models/pipeline_user_provided_input_definition.py
teaspoons_client/models/pipeline_with_details.py
teaspoons_client/models/prepare_pipeline_run_request_body.py
teaspoons_client/models/prepare_pipeline_run_response.py
teaspoons_client/models/start_pipeline_run_request_body.py
teaspoons_client/models/system_status.py
teaspoons_client/models/system_status_systems_value.py
teaspoons_client/models/update_pipeline_request_body.py
teaspoons_client/models/version_properties.py
terra_scientific_pipelines_service_client-0.0.0.dist-info/METADATA
terra_scientific_pipelines_service_client-0.0.0.dist-info/WHEEL
terra_scientific_pipelines_service_client-0.0.0.dist-info/top_level.txt
terra_scientific_pipelines_service_client-0.0.0.dist-info/RECORD
