Metadata-Version: 2.1
Name: terra-scientific-pipelines-service-client
Version: 0.0.0
Summary: Terra Scientific Pipelines Service
Home-page: 
Author: OpenAPI Generator community
Author-email: team@openapitools.org
Keywords: OpenAPI,OpenAPI-Generator,Terra Scientific Pipelines Service
Requires-Dist: urllib3 <2.1.0,>=1.25.3
Requires-Dist: python-dateutil
Requires-Dist: pydantic >=2
Requires-Dist: typing-extensions >=4.7.1
